wCountar/__init__.py
wCountar/find.py
wCountar/wcountar.py
wCountar-0.1.1.dist-info/METADATA
wCountar-0.1.1.dist-info/WHEEL
wCountar-0.1.1.dist-info/top_level.txt
wCountar-0.1.1.dist-info/RECORD
