Metadata-Version: 2.1
Name: wCountar
Version: 0.1.1
Summary: can count words so you dont have to make code to count words, or find them
Home-page: UNKNOWN
Author: fat.yellow.ducky
Author-email: <outlook_845155FE023A6EF8@outlook.com>
License: UNKNOWN
Keywords: geting,counting,words
Platform: UNKNOWN
Requires-Python: >=3.9.1
